<annotation>
	<folder></folder>
	<filename>images_jpg.rf.57eb54fc0d4444ddc38a113caa87c28f.jpg</filename>
	<path>images_jpg.rf.57eb54fc0d4444ddc38a113caa87c28f.jpg</path>
	<source>
		<database>roboflow.ai</database>
	</source>
	<size>
		<width>275</width>
		<height>183</height>
		<depth>3</depth>
	</size>
	<segmented>0</segmented>
	<object>
		<name>with_mask</name>
		<pose>Unspecified</pose>
		<truncated>0</truncated>
		<difficult>0</difficult>
		<occluded>0</occluded>
		<bndbox>
			<xmin>119</xmin>
			<xmax>233</xmax>
			<ymin>11</ymin>
			<ymax>133</ymax>
		</bndbox>
	</object>
</annotation>
